MANIFEST.in
README.rst
setup.py
django_sunrise.egg-info/PKG-INFO
django_sunrise.egg-info/SOURCES.txt
django_sunrise.egg-info/dependency_links.txt
django_sunrise.egg-info/requires.txt
django_sunrise.egg-info/top_level.txt
django_sunrise.egg-info/zip-safe
sunrise/__init__.py
sunrise/urls.py
sunrise/views.py
sunrise/cache/__init__.py
sunrise/cache/cache_mixin.py
sunrise/context_processors/__init__.py
sunrise/context_processors/mode_processors.py
sunrise/contrib/__init__.py
sunrise/contrib/addons/__init__.py
sunrise/contrib/addons/models.py
sunrise/contrib/addons/plugin_installer.py
sunrise/contrib/addons/routes.py
sunrise/contrib/addons/serializers.py
sunrise/contrib/addons/urls.py
sunrise/contrib/addons/views.py
sunrise/contrib/addons/viewsets.py
sunrise/contrib/addons/management/__init__.py
sunrise/contrib/addons/management/commands/__init__.py
sunrise/contrib/addons/management/commands/buildplugin.py
sunrise/contrib/addons/management/commands/createhstore.py
sunrise/contrib/addons/management/commands/createplugin.py
sunrise/contrib/addons/management/commands/destroyplugin.py
sunrise/contrib/addons/management/commands/install_plugins.py
sunrise/contrib/addons/management/commands/installplugin.py
sunrise/contrib/addons/migrations/0001_initial.py
sunrise/contrib/addons/migrations/__init__.py
sunrise/contrib/authentication/__init__.py
sunrise/contrib/authentication/handlers.py
sunrise/contrib/authentication/login_urls.py
sunrise/contrib/authentication/models.py
sunrise/contrib/authentication/routes.py
sunrise/contrib/authentication/serializers.py
sunrise/contrib/authentication/urls.py
sunrise/contrib/authentication/views.py
sunrise/contrib/authentication/viewsets.py
sunrise/contrib/authentication/migrations/0001_initial.py
sunrise/contrib/authentication/migrations/__init__.py
sunrise/contrib/cloud/__init__.py
sunrise/contrib/cloud/api.py
sunrise/contrib/cloud/sftp_api.py
sunrise/contrib/cloud/sunrise_cloud_api.py
sunrise/contrib/cloud/sync_ftp_s3.py
sunrise/contrib/cloud/sync_master.py
sunrise/contrib/cloud/urls.py
sunrise/contrib/cloud/views.py
sunrise/contrib/jobs/__init__.py
sunrise/contrib/jobs/job.py
sunrise/contrib/jobs/models.py
sunrise/contrib/jobs/routes.py
