Metadata-Version: 1.0
Name: django-sunrise
Version: 0.0.1
Summary: An enterprise application development framework
Home-page: UNKNOWN
Author: Partha.Konda
Author-email: parthasaradhi1992@gmail.com
License: UNKNOWN
Keywords: django-sunrise,sunrise
Platform: UNKNOWN
